{
    "name": "Bthree Dark",
    "is_dark": true,
    "fonts": {
        "faces": [
            {
                "font-family": "Inter",
                "src": [
                    {
                        "url": "/fonts/Inter.ttf",
                        "format": "ttf"
                    }
                ]
            }
        ],
        "general": "Inter, sans"
    },
    "colors": {
        "accent": "#34568B",
        "accent-color": "#34568B",
        "alert": "#C0392B",
        "focus-bg-color": "#4A90E2",
        "menu-selected-color": "#4A90E2",
        "other-user-pill-bg-color": "#4A90E2",
        "primary-color": "#27AE60",
        "reaction-row-button-selected-bg-color": "#4A90E2",
        "room-highlight-color": "#4A90E2",
        "roomlist-background-color": "#2C3E50",
        "roomlist-highlights-color": "#4f545c52",
        "roomlist-separator-color": "#40444b",
        "roomlist-text-color": "#dcddde",
        "roomlist-text-secondary-color": "#8e9297",
        "secondary-content": "#FFFFFF",
        "sidebar-color": "#202225",
        "tertiary-content": "#dcddde",
        "timeline-background-color": "#36393f",
        "timeline-highlights-color": "#04040512",
        "timeline-text-color": "#dcddde",
        "timeline-text-secondary-color": "#b9bbbe",
        "togglesw-off-color": "#72767d",
        "warning-color": "#F39C12"
    },
    "compound": {}
}
